qbiome/__init__.py
qbiome/data_formatter.py
qbiome/forecaster.py
qbiome/hypothesis.py
qbiome/mask_checker.py
qbiome/network.py
qbiome/qnet_orchestrator.py
qbiome/quantizer.py
qbiome/qutil.py
qbiome-0.0.67.dist-info/LICENSE
qbiome-0.0.67.dist-info/METADATA
qbiome-0.0.67.dist-info/WHEEL
qbiome-0.0.67.dist-info/top_level.txt
qbiome-0.0.67.dist-info/RECORD
