Metadata-Version: 2.1
Name: qbiome
Version: 0.0.67
Summary: Analyzing microbiome abundance data to infer deep structures
Home-page: https://github.com/zeroknowledgediscovery/qbiome
Download-URL: https://github.com/zeroknowledgediscovery/qbiome/archive/0.0.67.tar.gz
Author: zed.uchicago.edu
Author-email: ishanu@uchicago.edu
License: LICENSE
Keywords: microbiome,decision trees,machine learning,computational biology
Classifier: Development Status :: 4 - Beta
Classifier: Intended Audience :: Developers
Classifier: Intended Audience :: Science/Research
Classifier: Topic :: Scientific/Engineering :: Information Analysis
Classifier: Topic :: Scientific/Engineering :: Bio-Informatics
Classifier: Topic :: Software Development :: Libraries
Classifier: License :: OSI Approved :: MIT License
Classifier: Programming Language :: Python :: 3.6
Requires-Python: >=3.6
License-File: LICENSE
Requires-Dist: scikit-learn
Requires-Dist: scipy
Requires-Dist: numpy
Requires-Dist: pandas
Requires-Dist: joblib
Requires-Dist: quasinet
